lomo/__init__.py
lomo-0.0.1.dev0.dist-info/METADATA
lomo-0.0.1.dev0.dist-info/WHEEL
lomo-0.0.1.dev0.dist-info/top_level.txt
lomo-0.0.1.dev0.dist-info/RECORD
